{
  "meta": {"type": "hologram_reading", "version": "2.0"},
  "description": "Maps shell addresses to holographic readings (compressed representations)",
  "projection_law": "Any 4D slice through the 108D crystal contains the full information holographically",
  "reading_protocol": {
    "step_1": "Project query onto 4D SFCR vector",
    "step_2": "Rotate through 60 sigma views (icosahedral)",
    "step_3": "Expand to 240 E8 roots",
    "step_4": "Filter through sacred geometry",
    "step_5": "Modulate by momentum field",
    "step_6": "Commit via 4-gate witness"
  },
  "readings": {}
}
